mcp_liner/__init__.py
mcp_liner/_mcp_liner.dll
mcp_liner-0.2.5.dist-info/METADATA
mcp_liner-0.2.5.dist-info/WHEEL
mcp_liner-0.2.5.dist-info/entry_points.txt
mcp_liner-0.2.5.dist-info/licenses/LICENSE
mcp_liner-0.2.5.dist-info/RECORD
