Metadata-Version: 2.4
Name: mcp-liner
Version: 0.2.5
Summary: MCP Server for Liner configuration generation
Author-email: Benson Yan <fuxin04@gmail.com>
License:                     GNU AFFERO GENERAL PUBLIC LICENSE
License-File: LICENSE
Classifier: Programming Language :: Go
Classifier: Programming Language :: Python :: 3
Classifier: Topic :: System :: Systems Administration
Requires-Python: >=3.8
Provides-Extra: dev
Requires-Dist: pytest-cov>=4.1.0; extra == 'dev'
Requires-Dist: pytest>=7.4.0; extra == 'dev'
Requires-Dist: ruff>=0.1.0; extra == 'dev'
